spiir/__init__.py
spiir/logging.py
spiir/analysis/__init__.py
spiir/analysis/coinc.py
spiir/analysis/far_contour.py
spiir/analysis/zerolags.py
spiir/cli/__init__.py
spiir/cli/utils.py
spiir/data/__init__.py
spiir/data/parameter/__init__.py
spiir/data/parameter/distribution.py
spiir/data/waveform/__init__.py
spiir/data/waveform/cbc.py
spiir/data/waveform/iir/__init__.py
spiir/io/__init__.py
spiir/io/igwn/__init__.py
spiir/io/igwn/alert/__init__.py
spiir/io/igwn/alert/consumer.py
spiir/io/igwn/alert/consumers/__init__.py
spiir/io/igwn/alert/consumers/coinc.py
spiir/io/igwn/alert/consumers/event.py
spiir/io/igwn/alert/consumers/p_astro.py
spiir/io/igwn/alert/consumers/sealgw.py
spiir/io/ligolw/__init__.py
spiir/io/ligolw/array.py
spiir/io/ligolw/coinc.py
spiir/io/ligolw/ligolw.py
spiir/io/ligolw/param.py
spiir/io/ligolw/postcoh.py
spiir/io/ligolw/table.py
spiir/processing/__init__.py
spiir/processing/array.py
spiir/processing/mp.py
spiir/search/__init__.py
spiir/search/far.py
spiir/search/filter.py
spiir/search/p_astro/__init__.py
spiir/search/p_astro/bayes_factor.py
spiir/search/p_astro/mchirp_area.py
spiir/search/p_astro/models.py
spiir/search/skymap/__init__.py
spiir/search/skymap/plot.py
spiir/search/skymap/sealgw.py
spiir-0.0.5.dist-info/LICENSE
spiir-0.0.5.dist-info/METADATA
spiir-0.0.5.dist-info/WHEEL
spiir-0.0.5.dist-info/top_level.txt
spiir-0.0.5.dist-info/RECORD
